qualia_plugin_snn-2.5.0.dist-info/METADATA
qualia_plugin_snn-2.5.0.dist-info/WHEEL
qualia_plugin_snn-2.5.0.dist-info/entry_points.txt
qualia_plugin_snn-2.5.0.dist-info/licenses/LICENSE
qualia_plugin_snn/__init__.py
qualia_plugin_snn/dataaugmentation/pytorch/DataAugmentationPyTorchTimeStepsInData.py
qualia_plugin_snn/dataaugmentation/pytorch/__init__.py
qualia_plugin_snn/datamodel/EventDataModel.py
qualia_plugin_snn/datamodel/__init__.py
qualia_plugin_snn/dataset/DVSGesture.py
qualia_plugin_snn/dataset/DVSGestureWithPreprocessing.py
qualia_plugin_snn/dataset/EventDataset.py
qualia_plugin_snn/dataset/SHD.py
qualia_plugin_snn/dataset/__init__.py
qualia_plugin_snn/deployment/__init__.py
qualia_plugin_snn/deployment/qualia_codegen/Linux.py
qualia_plugin_snn/deployment/qualia_codegen/NucleoL452REP.py
qualia_plugin_snn/deployment/qualia_codegen/Windows.py
qualia_plugin_snn/deployment/qualia_codegen/__init__.py
qualia_plugin_snn/learningframework/SpikingJelly.py
qualia_plugin_snn/learningframework/SpikingJellyMultiStep.py
qualia_plugin_snn/learningframework/SpikingJellyMultiStepTimeStepsInData.py
qualia_plugin_snn/learningframework/SpikingJellyTimeStepsInData.py
qualia_plugin_snn/learningframework/__init__.py
qualia_plugin_snn/learningmodel/__init__.py
qualia_plugin_snn/learningmodel/pytorch/QuantizedSCNN.py
qualia_plugin_snn/learningmodel/pytorch/QuantizedSResNet.py
qualia_plugin_snn/learningmodel/pytorch/SCNN.py
qualia_plugin_snn/learningmodel/pytorch/SNN.py
qualia_plugin_snn/learningmodel/pytorch/SResNet.py
qualia_plugin_snn/learningmodel/pytorch/__init__.py
qualia_plugin_snn/learningmodel/pytorch/layers/CustomNode.py
qualia_plugin_snn/learningmodel/pytorch/layers/__init__.py
qualia_plugin_snn/learningmodel/pytorch/layers/quantized_SNN_layers.py
qualia_plugin_snn/learningmodel/pytorch/layers/spikingjelly/Add.py
qualia_plugin_snn/learningmodel/pytorch/layers/spikingjelly/QuantizedAdd.py
qualia_plugin_snn/learningmodel/pytorch/layers/spikingjelly/__init__.py
qualia_plugin_snn/learningmodel/pytorch/layers/spikingjelly/layers1d.py
qualia_plugin_snn/learningmodel/pytorch/layers/spikingjelly/layers2d.py
qualia_plugin_snn-2.5.0.dist-info/RECORD
